README.rst
setup.py
PyDataPro/Chain.py
PyDataPro/DataRow.py
PyDataPro/DataSource.py
PyDataPro/DataTable.py
PyDataPro/FileUtil.py
PyDataPro/LinkedMap.py
PyDataPro/Parameter.py
PyDataPro/PyDataHub.py
PyDataPro/PyEmail.py
PyDataPro/__init__.py
PyDataPro/config.py
PyDataPro.egg-info/PKG-INFO
PyDataPro.egg-info/SOURCES.txt
PyDataPro.egg-info/dependency_links.txt
PyDataPro.egg-info/top_level.txt
PyDataPro.egg-info/zip-safe