Metadata-Version: 1.1
Name: PyDataPro
Version: 1.0.1.1
Summary: This project is used for data development & data processing flow.
Home-page: https://pypi.python.org/pypi/PyDataPro
Author: FengChen
Author-email: 17801028323@163.com
License: MIT
Keywords: data processing python
Platform: UNKNOWN
Classifier: License :: OSI Approved :: MIT License
Classifier: Programming Language :: Python
Classifier: Intended Audience :: Developers
Classifier: Operating System :: OS Independent
